durabletask/__init__.py
durabletask/client.py
durabletask/deterministic.py
durabletask/task.py
durabletask/worker.py
durabletask/aio/__init__.py
durabletask/aio/client.py
durabletask/aio/internal/__init__.py
durabletask/aio/internal/grpc_interceptor.py
durabletask/aio/internal/shared.py
durabletask/internal/PROTO_SOURCE_COMMIT_HASH
durabletask/internal/grpc_interceptor.py
durabletask/internal/helpers.py
durabletask/internal/orchestrator_service_pb2.py
durabletask/internal/orchestrator_service_pb2.pyi
durabletask/internal/orchestrator_service_pb2_grpc.py
durabletask/internal/shared.py
durabletask_dapr-0.2.0a16.dist-info/licenses/LICENSE
durabletask_dapr-0.2.0a16.dist-info/METADATA
durabletask_dapr-0.2.0a16.dist-info/WHEEL
durabletask_dapr-0.2.0a16.dist-info/top_level.txt
durabletask_dapr-0.2.0a16.dist-info/RECORD
