Metadata-Version: 2.4
Name: durabletask-dapr
Version: 0.2.0a16
Summary: A Durable Task Client SDK for Python
License:     MIT License
Project-URL: repository, https://github.com/dapr/durabletask-python
Project-URL: changelog, https://github.com/dapr/durabletask-python/blob/main/CHANGELOG.md
Keywords: durable,task,workflow
Classifier: Development Status :: 3 - Alpha
Classifier: Programming Language :: Python :: 3
Classifier: License :: OSI Approved :: MIT License
Requires-Python: >=3.10
License-File: LICENSE
Requires-Dist: grpcio
Requires-Dist: protobuf<7.0.0,>=6.31.1
Requires-Dist: asyncio
Provides-Extra: dev
Requires-Dist: pytest; extra == "dev"
Requires-Dist: pytest-asyncio>=0.23; extra == "dev"
Requires-Dist: tox>=4.0.0; extra == "dev"
Requires-Dist: pytest-cov; extra == "dev"
Requires-Dist: ruff; extra == "dev"
Requires-Dist: grpcio-tools==1.75.1; extra == "dev"
Dynamic: license-file
